README.md
setup.cfg
setup.py
iwlearn/__init__.py
iwlearn/base.py
iwlearn/datasources.py
iwlearn/mongo.py
iwlearn/preprocessors.py
iwlearn/repo.py
iwlearn/samples.py
iwlearn/models/__init__.py
iwlearn/models/based_on_keras.py
iwlearn/models/based_on_sklearn.py
iwlearn/storage/__init__.py
iwlearn/storage/base.py
iwlearn/storage/filestore.py
iwlearn/training/__init__.py
iwlearn/training/dataset.py
iwlearn/training/dataset_operations.py
iwlearn3.egg-info/PKG-INFO
iwlearn3.egg-info/SOURCES.txt
iwlearn3.egg-info/dependency_links.txt
iwlearn3.egg-info/not-zip-safe
iwlearn3.egg-info/requires.txt
iwlearn3.egg-info/top_level.txt