Metadata-Version: 1.1
Name: iwlearn3
Version: 0.1.4
Summary: Immowelt Machine Learning Framework (Python 3)
Home-page: https://github.com/mfridental/iwlearn
Author: Maxim Fridental (Maintainer)
Author-email: maxim@fridental.de
License: Apache2
Download-URL: https://github.com/mfridental/iwlearn/archive/0.1.4.tar.gz
Keywords: Scikit-Learn,Tensorflow,Keras,Machine Learning
Platform: UNKNOWN
Classifier: Programming Language :: Python :: 3
